hello.py
codebolt-0.1.0.dist-info/METADATA
codebolt-0.1.0.dist-info/WHEEL
codebolt-0.1.0.dist-info/top_level.txt
codebolt-0.1.0.dist-info/RECORD
