Metadata-Version: 2.2
Name: codebolt
Version: 0.1.0
Summary: Codebolt Application
Requires-Python: >=3.13
